<?xml version="1.0" encoding="utf-8"?>
<?xml-stylesheet version="1.0" href="../../stylesheets/source2html.xsl" type="text/xsl"?>
<sourceDataSet xmlns:common="http://lca.jrc.it/ILCD/Common" xmlns="http://lca.jrc.it/ILCD/Source" xmlns:xsi="http://www.w3.org/2001/XMLSchema-instance" version="1.1" xsi:schemaLocation="http://lca.jrc.it/ILCD/Source ../../schemas/ILCD_SourceDataSet.xsd">
	<sourceInformation>
		<dataSetInformation>
			<common:UUID>d3278c5c-33ae-4924-b091-aef88f902037</common:UUID>
			<common:shortName xml:lang="en">邓红琳,赵文彬,袁立鹤.钻井液不落地技术在大牛地气田的应用[J].断块油气田,2014,21(01):97-99.</common:shortName>
			<classificationInformation>
				<common:classification>
					<common:class level="0">Publications and communications</common:class>
				</common:classification>
			</classificationInformation>
			<sourceCitation>https://doi.org/10.6056/dkyqt201401023</sourceCitation>
			<publicationType>Article in periodical</publicationType>
		</dataSetInformation>
	</sourceInformation>
	<administrativeInformation>
		<dataEntryBy>
			<common:timeStamp>2023-07-27T16:40:58+08:00</common:timeStamp>
			<common:referenceToDataSetFormat type="source data set" refObjectId="a97a0155-0234-4b87-b4ce-a45da52f2a40" uri="../sources/a97a0155-0234-4b87-b4ce-a45da52f2a40.xml">
				<common:shortDescription xml:lang="en">ILCD format</common:shortDescription>
			</common:referenceToDataSetFormat>
		</dataEntryBy>
		<publicationAndOwnership>
			<common:dataSetVersion>01.00.000</common:dataSetVersion>
		</publicationAndOwnership>
	</administrativeInformation>
</sourceDataSet>
