<?xml version="1.0" encoding="utf-8"?>
<?xml-stylesheet version="1.0" href="../../stylesheets/flow2html.xsl" type="text/xsl"?>
<flowDataSet xmlns:common="http://lca.jrc.it/ILCD/Common" xmlns="http://lca.jrc.it/ILCD/Flow" xmlns:xsi="http://www.w3.org/2001/XMLSchema-instance" version="1.1" locations="../ILCDLocations.xml" xsi:schemaLocation="http://lca.jrc.it/ILCD/Flow ../../schemas/ILCD_FlowDataSet.xsd">
	<flowInformation>
		<dataSetInformation>
			<common:UUID>2e6d00db-7f50-43db-b13d-f8d4c14e51c5</common:UUID>
			<name>
				<baseName xml:lang="en">Copper Foil</baseName>
				<baseName xml:lang="zh">铜箔</baseName>
			</name>
			<common:synonyms xml:lang="en">Rolled Annealed Copper Foil; Electrodeposited Copper Foil,铜箔</common:synonyms>
			<classificationInformation>
				<common:classification>
					<common:category level="0">Materials production</common:category>
					<common:category level="1">Metals and semimetals</common:category>
				</common:classification>
			</classificationInformation>
			<sumFormula>Cu</sumFormula>
			<common:generalComment xml:lang="en">Copper foil is a thin and malleable material with a high melting point, making it suitable for many industrial and commercial tasks. It is the base copper thickness applied on outer and inner layers and can be pre-attached by the laminate manufacturer to a base material core or introduced in a multi layer board as copper foil before pressing. It is sturdy due to its good mechanical strength and has the advantage of absence of resonance in thermal region. It is a kind of negative electrolytic material, divided into rolled annealed copper (RA copper foil) and electrodeposited copper foil (ED copper foil).</common:generalComment>
			<common:generalComment xml:lang="zh">铜箔是一种薄而可塑的材料，熔点高，适用于许多工业和商业任务。它是应用于外层和内层的基铜厚度，可由层压板制造商预先粘贴到基材芯上，或在压制前作为铜箔引入多层板中。它具有良好的机械强度和热区无共振的优点，因此非常坚固。它是一种负电解材料，分为压延退火铜箔（RA 铜箔）和电沉积铜箔（ED 铜箔）。</common:generalComment>
		</dataSetInformation>
		<quantitativeReference>
			<referenceToReferenceFlowProperty>0</referenceToReferenceFlowProperty>
		</quantitativeReference>
	</flowInformation>
	<modellingAndValidation>
		<LCIMethod>
			<typeOfDataSet>Product flow</typeOfDataSet>
		</LCIMethod>
	</modellingAndValidation>
	<administrativeInformation>
		<dataEntryBy>
			<common:timeStamp>2023-10-22T17:22:04.089897+08:00</common:timeStamp>
			<common:referenceToDataSetFormat type="source data set" refObjectId="a97a0155-0234-4b87-b4ce-a45da52f2a40" uri="../sources/a97a0155-0234-4b87-b4ce-a45da52f2a40.xml">
				<common:shortDescription xml:lang="en">ILCD format</common:shortDescription>
			</common:referenceToDataSetFormat>
		</dataEntryBy>
		<publicationAndOwnership>
			<common:dataSetVersion>01.00.000</common:dataSetVersion>
		</publicationAndOwnership>
	</administrativeInformation>
	<flowProperties>
		<flowProperty dataSetInternalID="0">
			<referenceToFlowPropertyDataSet type="flow property data set" refObjectId="93a60a56-a3c8-11da-a746-0800200b9a66" version="00.00.000" uri="../flowproperties/93a60a56-a3c8-11da-a746-0800200b9a66.xml">
				<common:shortDescription xml:lang="en">Mass</common:shortDescription>
			</referenceToFlowPropertyDataSet>
			<meanValue>1.0</meanValue>
		</flowProperty>
	</flowProperties>
</flowDataSet>
