<?xml version="1.0" encoding="UTF-8" standalone="no"?>
<?xml-stylesheet type='text/xsl' href='../../stylesheets/flow2html.xsl'?><flowDataSet xmlns="http://lca.jrc.it/ILCD/Flow" xmlns:common="http://lca.jrc.it/ILCD/Common" xmlns:ecn="http://eplca.jrc.ec.europa.eu/ILCD/Extensions/2018/ECNumber" xmlns:xsi="http://www.w3.org/2001/XMLSchema-instance" version="1.1" xsi:schemaLocation="http://lca.jrc.it/ILCD/Flow ../../schemas/ILCD_FlowDataSet.xsd">
  <flowInformation>
    <dataSetInformation>
      <common:UUID>a49b4f24-df08-43f2-9395-8ed2b44a55a9</common:UUID>
      <name>
        <baseName xml:lang="en">2,2-bis(chloromethyl)trimethylene bis(bis(2-chloroethyl)phosphate)</baseName>
</name>
      <common:synonyms xml:lang="en">organic;2,2-bis(chloromethyl)trimethylenebis(bis(2-chloroethyl)phosphate);amgardv6(nolongermarketed);antiblaze100(nolongermarketed);antiblazetl-10-st;antiblazev6(nolongermarketed);antiblazev6ls(nolongermarketedineu);antiblazev66;phireguardelf-601;phireguardelf-606;phosgard2xc20(nolongermarketed);tl-10-st;tolgardv6(nolongermarketed)</common:synonyms>
      <classificationInformation>
        <common:elementaryFlowCategorization>
          <common:category level="0">Emissions</common:category>
          <common:category level="1">Emissions to water</common:category>
          <common:category level="2">Emissions to fresh water</common:category>
</common:elementaryFlowCategorization>
</classificationInformation>
      <CASNumber>38051-10-4</CASNumber>
      <common:generalComment xml:lang="en">Reference elementary flow of the International Reference Life Cycle Data System (ILCD).</common:generalComment>
	  <common:other>
<ecn:ECNumber>253-760-2</ecn:ECNumber>
</common:other>
</dataSetInformation>
    <quantitativeReference>
      <referenceToReferenceFlowProperty>0</referenceToReferenceFlowProperty>
</quantitativeReference>
</flowInformation>
  <modellingAndValidation>
    <LCIMethod>
      <typeOfDataSet>Elementary flow</typeOfDataSet>
</LCIMethod>
    <complianceDeclarations>
      <compliance>
        <common:referenceToComplianceSystem refObjectId="9ba3ac1e-6797-4cc0-afd5-1b8f7bf28c6a" type="source data set" uri="../sources/9ba3ac1e-6797-4cc0-afd5-1b8f7bf28c6a.xml">
          <common:shortDescription xml:lang="en">ILCD Data Network - compliance (non-Process)</common:shortDescription>
</common:referenceToComplianceSystem>
        <common:approvalOfOverallCompliance>Fully compliant</common:approvalOfOverallCompliance>
</compliance>
</complianceDeclarations>
</modellingAndValidation>
  <administrativeInformation>
    <dataEntryBy>
      <common:timeStamp>2018-07-12T15:52:21.041+01:00</common:timeStamp>
      <common:referenceToDataSetFormat refObjectId="a97a0155-0234-4b87-b4ce-a45da52f2a40" type="source data set" uri="../sources/a97a0155-0234-4b87-b4ce-a45da52f2a40.xml">
        <common:shortDescription xml:lang="en">ILCD format</common:shortDescription>
</common:referenceToDataSetFormat>
</dataEntryBy>
    <publicationAndOwnership>
      <common:dataSetVersion>00.00.002</common:dataSetVersion>
      <common:permanentDataSetURI>http://eplca.jrc.ec.europa.eu/EF-node/resource/flows/a49b4f24-df08-43f2-9395-8ed2b44a55a9.xml</common:permanentDataSetURI>
</publicationAndOwnership>
</administrativeInformation>
  <flowProperties>
    <flowProperty dataSetInternalID="0">
      <referenceToFlowPropertyDataSet refObjectId="93a60a56-a3c8-11da-a746-0800200b9a66" type="flow property data set" uri="../flowproperties/93a60a56-a3c8-11da-a746-0800200b9a66.xml">
        <common:shortDescription xml:lang="en">Mass</common:shortDescription>
</referenceToFlowPropertyDataSet>
      <meanValue>1.0</meanValue>
</flowProperty>
</flowProperties>
</flowDataSet>
