<?xml version="1.0" encoding="utf-8"?>
<?xml-stylesheet version="1.0" href="../../stylesheets/flow2html.xsl" type="text/xsl"?>
<flowDataSet xmlns:common="http://lca.jrc.it/ILCD/Common" xmlns="http://lca.jrc.it/ILCD/Flow" xmlns:xsi="http://www.w3.org/2001/XMLSchema-instance" version="1.1" locations="../ILCDLocations.xml" xsi:schemaLocation="http://lca.jrc.it/ILCD/Flow ../../schemas/ILCD_FlowDataSet.xsd">
	<flowInformation>
		<dataSetInformation>
			<common:UUID>f4ebe6e5-4652-4be0-a36e-478b1f4d2289</common:UUID>
			<name>
				<baseName xml:lang="en">Coke ash</baseName>
				<baseName xml:lang="zh">焦炭灰分</baseName>
			</name>
			<common:synonyms xml:lang="en">Coal combustion residuals; CCRs; Fly ash; Bottom ash</common:synonyms>
			<common:synonyms xml:lang="zh">Coal combustion residuals; CCRs; Fly ash; Bottom ash</common:synonyms>
			<classificationInformation>
				<common:classification>
					<common:category level="0">Wastes</common:category>
					<common:category level="1">Other waste</common:category>
				</common:classification>
			</classificationInformation>
			<CASNumber>Not provided</CASNumber>
			<common:generalComment xml:lang="en">Coke ash, also referred to as coal combustion residuals or CCRs, is produced primarily from the burning of coal in coal-fired power plants. It includes a number of by-products produced from burning coal, such as fly ash and bottom ash. Coke ash is conducive to slurrying, as the ash content in coal helps to reduce slurry viscosity and improve stability. By gasification of the coke slurry, many important products, including hydrogen, liquid fuels and chemicals, can be obtained.</common:generalComment>
			<common:generalComment xml:lang="zh">焦炭灰，又称燃煤残渣或 CCR，主要产生于燃煤发电厂的燃煤过程。它包括燃煤产生的一些副产品，如粉煤灰和底灰。焦炭灰有利于浆化，因为煤中的灰分有助于降低浆液粘度并提高稳定性。通过对焦炭浆进行气化，可以获得许多重要产品，包括氢气、液体燃料和化学品。</common:generalComment>
			<sumFormula>Not provided</sumFormula>
		</dataSetInformation>
		<quantitativeReference>
			<referenceToReferenceFlowProperty>0</referenceToReferenceFlowProperty>
		</quantitativeReference>
	</flowInformation>
	<modellingAndValidation>
		<LCIMethod>
			<typeOfDataSet>Product flow</typeOfDataSet>
		</LCIMethod>
	</modellingAndValidation>
	<administrativeInformation>
		<dataEntryBy>
			<common:timeStamp>2023-11-20T15:21:33.189970+08:00</common:timeStamp>
			<common:referenceToDataSetFormat type="source data set" refObjectId="a97a0155-0234-4b87-b4ce-a45da52f2a40" uri="../sources/a97a0155-0234-4b87-b4ce-a45da52f2a40.xml">
				<common:shortDescription xml:lang="en">ILCD format</common:shortDescription>
			</common:referenceToDataSetFormat>
		</dataEntryBy>
		<publicationAndOwnership>
			<common:dataSetVersion>01.00.000</common:dataSetVersion>
		</publicationAndOwnership>
	</administrativeInformation>
	<flowProperties>
		<flowProperty dataSetInternalID="0">
			<referenceToFlowPropertyDataSet type="flow property data set" refObjectId="93a60a56-a3c8-11da-a746-0800200b9a66" version="00.00.000" uri="../flowproperties/93a60a56-a3c8-11da-a746-0800200b9a66.xml">
				<common:shortDescription xml:lang="en">Mass</common:shortDescription>
			</referenceToFlowPropertyDataSet>
			<meanValue>1.0</meanValue>
		</flowProperty>
	</flowProperties>
</flowDataSet>
