<?xml version="1.0" encoding="UTF-8" standalone="yes"?><?xml-stylesheet type='text/xsl' href='../../stylesheets/flow2html.xsl'?>
<flowDataSet xmlns:common="http://lca.jrc.it/ILCD/Common" xmlns="http://lca.jrc.it/ILCD/Flow" xmlns:xsi="http://www.w3.org/2001/XMLSchema-instance" version="1.1" xsi:schemaLocation="http://lca.jrc.it/ILCD/Flow ../../schemas/ILCD_FlowDataSet.xsd">
    <flowInformation>
        <dataSetInformation>
            <common:UUID>fe0acd60-3ddc-11dd-b027-0050c2490048</common:UUID>
            <name>
                <baseName xml:lang="en">betasan</baseName>
            </name>
            <common:synonyms xml:lang="en">(N-(2-Mercaptoethyl)benzenesulfonamide);AC1L20O8;BENSULIDE;Bensulide [BSI:ISO];Benzenesulfonamide, N-(2-mercaptoethyl)-, S-ester with O,O-diisopropylphosphorodithioate;Benzulfide;Betamec;Betasan E;Betasan G;Betasan [OBSOLETE];Disan;Disan (pesticide);Exporsan;Kayaphenone;N-(2-(O,O-Diisopropyldithiophosphoryl)ethyl)benzenesulfonamide;N-(2-Ethylthio)benzene sulphonamide-S,O,O-diisopropylphosphorodithioate;N-(2-Mercaptoethyl)benzenesulfonamide S-(O,O-diisopropyl phosphorodithioate);N-(2-Mercaptoethylbenzene)sulfonamide S-(O,O-diisopropylphosphorodithioate);N-(beta-O,O-Diisopropyldithiophosphorylethyl)benzenesulfonamide;N-[2-di(propan-2-yloxy)phosphinothioylsulfanylethyl]benzenesulfonamide;O,O-Bis(1-methylethyl) S-(2-((phenylsulfonyl)amino)ethyl)pheosphorodithioate;O,O-Bis(1-methylethyl) S-(2-((phenylsulfonyl)amino)ethyl)phosphorodithioate;O,O-Bis(1-methylethyl) S-(2-((phenylsulfonyl)amino)ethyl)phosphorodithioate (9CI);O,O-Bis(1-methylethyl)-S-(2-((phenylsulfonyl)amino)ethyl) phosphorodithioate;O,O-Di-isopropyl S-2-phenylsulphonylaminoethyl phosphorodithioate;O,O-Diisopropyl 2-(benzenesulfonamido)ethyl dithiophosphate;O,O-Diisopropyl S-(2-benzenesulfonylaminoethyl) phosphorodithioate;O,O-Diisopropyl dithiophosphate S-ester with N-(2-mercaptoethyl)benzenesulphonamide;O,O-Diisopropyl phosphorodithioate S-ester with N-(2-mercaptoethyl)benzenesulfonamide;O,O-Diisopropyl phosphorothioate S-ester with N-(2-mercaptoethyl)benzenesulfonamide;O,O-diisopropyl S-{2-[(phenylsulfonyl)amino]ethyl} dithiophosphate;Phosphorodithioic acid, O,O-bis(1-methylethyl) S-(2-((phenylsulfonyl)amino)ethyl) ester;Phosphorodithioic acid, O,O-bis(1-methylethyl) S-[2-[(phenylsulfonyl)amino]ethyl] ester;Phosphorodithioic acid, O,O-diisopropyl ester, S-ester with N-(2-mercaptoethyl)benzenesulfonamide;Pre-San;Prefar;Prefar E;Prefer;R 4461;R-4461;S-(O,O-Diisopropyl phosphorodithioate) ester of N-(2-Mercaptoethyl)benzenesulfonamide;S-(O,O-Diisopropylphosphorodithioate) of N-(2-mercaptoethyl)benzenesulfonamide;S-2-Benzenesulfonamidoethyl O,O-di-isopropyl phosphorodithioate;S-2-Benzenesulphonamidoethyl O,O-diisopropyl phosphorodithioate;S-beta-(Benzenesulfonamido)Ethyl O,O-diisopropyl dithiophosphate;SAP (herbicide)</common:synonyms>
            <classificationInformation>
                <common:elementaryFlowCategorization>
                    <common:category level="0">Emissions</common:category>
                    <common:category level="1">Emissions to water</common:category>
                    <common:category level="2">Emissions to water, unspecified</common:category>
                </common:elementaryFlowCategorization>
            </classificationInformation>
            <CASNumber>000741-58-2</CASNumber>
            <common:generalComment xml:lang="en">Reference elementary flow of the International Reference Life Cycle Data System (ILCD).</common:generalComment>
        </dataSetInformation>
        <quantitativeReference>
            <referenceToReferenceFlowProperty>0</referenceToReferenceFlowProperty>
        </quantitativeReference>
    </flowInformation>
    <modellingAndValidation>
        <LCIMethod>
            <typeOfDataSet>Elementary flow</typeOfDataSet>
        </LCIMethod>
        <complianceDeclarations>
            <compliance>
                <common:referenceToComplianceSystem type="source data set" refObjectId="9ba3ac1e-6797-4cc0-afd5-1b8f7bf28c6a" uri="../sources/9ba3ac1e-6797-4cc0-afd5-1b8f7bf28c6a.xml">
                    <common:shortDescription xml:lang="en">ILCD Data Network - compliance (non-Process)</common:shortDescription>
                </common:referenceToComplianceSystem>
                <common:approvalOfOverallCompliance>Fully compliant</common:approvalOfOverallCompliance>
            </compliance>
        </complianceDeclarations>
    </modellingAndValidation>
    <administrativeInformation>
        <dataEntryBy>
            <common:timeStamp>2012-01-12T15:51:22.564+01:00</common:timeStamp>
            <common:referenceToDataSetFormat type="source data set" refObjectId="a97a0155-0234-4b87-b4ce-a45da52f2a40" uri="../sources/a97a0155-0234-4b87-b4ce-a45da52f2a40.xml">
                <common:shortDescription xml:lang="en">ILCD format</common:shortDescription>
            </common:referenceToDataSetFormat>
        </dataEntryBy>
        <publicationAndOwnership>
            <common:dataSetVersion>03.00.000</common:dataSetVersion>
            <common:permanentDataSetURI>http://lca.jrc.ec.europa.eu/lcainfohub/datasets/ilcd/flows/fe0acd60-3ddc-11dd-b027-0050c2490048.xml</common:permanentDataSetURI>
        </publicationAndOwnership>
    </administrativeInformation>
    <flowProperties>
        <flowProperty dataSetInternalID="0">
            <referenceToFlowPropertyDataSet type="flow property data set" refObjectId="93a60a56-a3c8-11da-a746-0800200b9a66" uri="../flowproperties/93a60a56-a3c8-11da-a746-0800200b9a66.xml">
                <common:shortDescription xml:lang="en">Mass</common:shortDescription>
            </referenceToFlowPropertyDataSet>
            <meanValue>1.0</meanValue>
        </flowProperty>
    </flowProperties>
</flowDataSet>
