<?xml version="1.0" encoding="utf-8"?>
<?xml-stylesheet version="1.0" href="../../stylesheets/process2html.xsl" type="text/xsl"?>
<processDataSet xmlns:common="http://lca.jrc.it/ILCD/Common" xmlns="http://lca.jrc.it/ILCD/Process" xmlns:xsi="http://www.w3.org/2001/XMLSchema-instance" version="1.1" locations="../ILCDLocations.xml" xsi:schemaLocation="http://lca.jrc.it/ILCD/Process ../../schemas/ILCD_ProcessDataSet.xsd">
	<processInformation>
		<dataSetInformation>
			<common:UUID>0fffdd63-f7dc-4ea8-9de5-a243f3a6204a</common:UUID>
			<name>
				<baseName xml:lang="en">Waste water - treated ; Soil ex-situ remediation ; Ex-situ thermal desorption ; Soil excavation ; Foundation pit dewatering</baseName>
				<baseName xml:lang="zh">处置后废水;土壤异位修复;异位热脱附;土壤挖掘;基坑降水</baseName>
			</name>
			<classificationInformation>
				<common:classification>
					<common:class level="0">Other Services</common:class>
					<common:class level="1">Repair and maintenance</common:class>
				</common:classification>
			</classificationInformation>
			<common:generalComment xml:lang="zh">挖掘并运输到异位热脱附设备的土壤，在该环节进行热脱附，以实现污染物的去除。</common:generalComment>
			<common:generalComment xml:lang="en">Excavated and transport the soil to the ectopic thermal desorption equipment, where thermal desorption is carried out to achieve the removal of pollutants.</common:generalComment>
		</dataSetInformation>
		<quantitativeReference type="Reference flow(s)">
			<functionalUnitOrOther xml:lang="en">The functional unit of LCA was defined as the treatment of 1000 m3 of contaminated soil to meet the risk-based remediation targets.</functionalUnitOrOther>
			<referenceToReferenceFlow>1</referenceToReferenceFlow>
		</quantitativeReference>
		<time>
			<common:referenceYear>2022</common:referenceYear>
		</time>
		<geography>
			<locationOfOperationSupplyOrProduction location="WH-HUB-CN">
				<descriptionOfRestrictions xml:lang="en">A contaminated site located in Wuhan, China was selected as the case study. Approximately 1.25 million m3 of soil was found contaminated, and forty types of VOCs, SVOCs, and heavy metal contaminants were measured in the soil.</descriptionOfRestrictions>
				<descriptionOfRestrictions xml:lang="zh">选择位于中国武汉的一个受污染场地作为案例研究。大约125万m3的土壤被受到污染，土壤中测量到40种VOC、SVOC和重金属污染物。</descriptionOfRestrictions>
			</locationOfOperationSupplyOrProduction>
		</geography>
		<technology>
			<technologyDescriptionAndIncludedProcesses xml:lang="en">Contaminated soil is excavated and transferred into a rotatory thermal reactor for treatment under vacuumed and low oxygen conditions. The reactor is heated using flame, steam, or hot oil to remove organic contaminants (&gt; 99%) and moisture from the soil. The vaporized contaminants enter a combustion chamber as gases or fine particles and are destroyed by incineration. The exhaust gas is emitted after proper treatment.</technologyDescriptionAndIncludedProcesses>
			<technologyDescriptionAndIncludedProcesses xml:lang="zh">受污染的土壤被挖掘并转移到旋转式热反应器中，在真空和低氧条件下进行处理。使用火焰、蒸汽或热油加热反应器，以去除土壤中的有机污染物（&gt;99%）和水分。蒸发的污染物以气体或细颗粒的形式进入燃烧室，并被焚烧破坏。废气经过适当处理后排放。</technologyDescriptionAndIncludedProcesses>
			<technologicalApplicability xml:lang="en">The soil ex-situ remediation process using ex-situ thermal desorption is designed for the treatment of contaminated soil primarily from industrial sites. This process is applicable for the removal of a wide range of soil contaminants, including volatile organic compounds (VOCs), semi-volatile organic compounds (SVOCs), and heavy metals. The treated soil is meant for sites where risk-based remediation targets are set to manage environmental hazards effectively.</technologicalApplicability>
			<technologicalApplicability xml:lang="zh">土壤异位修复过程使用异位热脱附技术，主要用于工业场地受污染土壤的处理。该过程适用于去除各种土壤污染物，包括挥发性有机化合物（VOCs）、半挥发性有机化合物（SVOCs）和重金属。经处理的土壤适用于设定风险基准修复目标的场所，有效管理环境危害。</technologicalApplicability>
			<referenceToTechnologyFlowDiagrammOrPicture type="source data set" refObjectId="d1b69a20-0e3e-7cb6-e274-9543d4dbe143" uri="../sources/d1b69a20-0e3e-7cb6-e274-9543d4dbe143.xml">
				<common:shortDescription xml:lang="en">A9WIbtG1ToVnXrxhmelcZYjDnGg.png</common:shortDescription>
			</referenceToTechnologyFlowDiagrammOrPicture>
		</technology>
	</processInformation>
	<modellingAndValidation>
		<LCIMethodAndAllocation>
			<typeOfDataSet>Unit process, single operation</typeOfDataSet>
			<LCIMethodPrinciple>Not applicable</LCIMethodPrinciple>
			<deviationsFromLCIMethodPrinciple xml:lang="en">None</deviationsFromLCIMethodPrinciple>
			<deviationsFromLCIMethodPrinciple xml:lang="zh">无</deviationsFromLCIMethodPrinciple>
			<deviationsFromModellingConstants xml:lang="en">None</deviationsFromModellingConstants>
			<deviationsFromModellingConstants xml:lang="zh">无</deviationsFromModellingConstants>
		</LCIMethodAndAllocation>
		<dataSourcesTreatmentAndRepresentativeness>
			<deviationsFromCutOffAndCompletenessPrinciples xml:lang="en">None</deviationsFromCutOffAndCompletenessPrinciples>
			<deviationsFromCutOffAndCompletenessPrinciples xml:lang="zh">无</deviationsFromCutOffAndCompletenessPrinciples>
			<deviationsFromSelectionAndCombinationPrinciples xml:lang="en">None</deviationsFromSelectionAndCombinationPrinciples>
			<deviationsFromSelectionAndCombinationPrinciples xml:lang="zh">无</deviationsFromSelectionAndCombinationPrinciples>
			<deviationsFromTreatmentAndExtrapolationPrinciples xml:lang="en">None</deviationsFromTreatmentAndExtrapolationPrinciples>
			<deviationsFromTreatmentAndExtrapolationPrinciples xml:lang="zh">无</deviationsFromTreatmentAndExtrapolationPrinciples>
			<referenceToDataSource type="source data set" refObjectId="2c32fe1d-9e2c-47c4-baa6-6b395ed6fa50" uri="../sources/2c32fe1d-9e2c-47c4-baa6-6b395ed6fa50.xml">
				<common:shortDescription xml:lang="en">Guangji H ,Huan L ,Chang C , et al. Selection of green remediation alternatives for chemical industrial sites: An integrated life cycle assessment and fuzzy synthetic evaluation approach. Science of the Total Environment, 2022, 845 157211-157211.</common:shortDescription>
				<common:shortDescription xml:lang="zh">Guangji H ,Huan L ,Chang C , et al. Selection of green remediation alternatives for chemical industrial sites: An integrated life cycle assessment and fuzzy synthetic evaluation approach. Science of the Total Environment, 2022, 845 157211-157211.</common:shortDescription>
			</referenceToDataSource>
			<useAdviceForDataSet xml:lang="en">When utilizing this dataset for Life Cycle Assessment (LCA) of soil remediation, users should note that only the impacts from the operational phase of on-site remediation have been assessed. Hence, exclusion of the manufacturing of equipment impacts needs to be consistently applied in comparative studies. It is essential to apply the functional unit of the treatment of 1000 m3 of contaminated soil when gauging and comparing the efficacy of this process to others. Additionally, users need to ensure that the dataset is suitable for their specific regional context, especially if used in a different geographical location than Wuhan, China.</useAdviceForDataSet>
			<useAdviceForDataSet xml:lang="zh">在使用该数据集进行土壤修复生命周期评价（LCA）时，用户应注意，仅评估了现场修复操作阶段的影响。因此，在比较研究中需要一致地排除设备制造影响。在衡量和比较该过程与其他过程的效果时，必须应用1000立方米受污染土壤处理的功能单元。此外，用户需要确保数据集适用于他们的具体区域背景，特别是如果在中国武汉以外的不同地理位置使用时。</useAdviceForDataSet>
		</dataSourcesTreatmentAndRepresentativeness>
		<completeness>
			<common:other xml:lang="en">Only impacts from the operational phase of site remediation were assessed, while impacts from the manufacturing of equipment were not considered in the LCA.</common:other>
			<common:other xml:lang="zh">仅评估了现场修复操作阶段的影响，而LCA中未考虑设备制造的影响。</common:other>
		</completeness>
		<validation>
			<review type="Dependent internal review">
				<common:reviewDetails xml:lang="en">Inventory: The internal review was done by several iteration steps concerning raw data validation, raw data documentation, representativity, completeness and consistency of modelling with regard to ISO 14040 and 14044.</common:reviewDetails>
				<common:reviewDetails xml:lang="zh">清单： 内部审查通过几个迭代步骤完成，涉及原始数据验证、原始数据记录、代表性、完整性、与 ISO 14040 和 14044 有关的建模的一致性。</common:reviewDetails>
				<common:referenceToNameOfReviewerAndInstitution refObjectId="f4b4c314-8c4c-4c83-968f-5b3c7724f6a8" type="contact data set" uri="../contacts/f4b4c314-8c4c-4c83-968f-5b3c7724f6a8.xml">
					<common:shortDescription xml:lang="en">Tiangong LCI Data Working Group</common:shortDescription>
					<common:shortDescription xml:lang="zh">天工LCI数据工作小组</common:shortDescription>
				</common:referenceToNameOfReviewerAndInstitution>
			</review>
		</validation>
	</modellingAndValidation>
	<administrativeInformation>
		<dataGenerator>
			<common:referenceToPersonOrEntityGeneratingTheDataSet type="contact data set" refObjectId="b06c9239-9861-46c9-9117-783f6b998ead" uri="../contacts/b06c9239-9861-46c9-9117-783f6b998ead.xml" version="01.00.000">
				<common:shortDescription xml:lang="en">Yang Xintong, yangxt@caep.org.cn</common:shortDescription>
				<common:shortDescription xml:lang="zh">杨欣桐, yangxt@caep.org.cn</common:shortDescription>
			</common:referenceToPersonOrEntityGeneratingTheDataSet>
			<common:other xml:lang="en">yangxt@caep.org.cn</common:other>
			<common:other xml:lang="zh">yangxt@caep.org.cn</common:other>
		</dataGenerator>
		<dataEntryBy>
			<common:timeStamp>2024-03-25T15:22:09+08:00</common:timeStamp>
		</dataEntryBy>
		<publicationAndOwnership>
			<common:dateOfLastRevision>2024-03-25T19:09:11.752990+08:00</common:dateOfLastRevision>
			<common:dataSetVersion>00.01.004</common:dataSetVersion>
			<common:permanentDataSetURI>https://lcadata.tiangong.world/showProcess.xhtml?uuid=0fffdd63-f7dc-4ea8-9de5-a243f3a6204a&amp;amp;version=01.00.000&amp;amp;stock=TianGong</common:permanentDataSetURI>
			<common:referenceToOwnershipOfDataSet refObjectId="f4b4c314-8c4c-4c83-968f-5b3c7724f6a8" type="contact data set" uri="../contacts/f4b4c314-8c4c-4c83-968f-5b3c7724f6a8.xml">
				<common:shortDescription xml:lang="en">Tiangong LCI Data Working Group</common:shortDescription>
				<common:shortDescription xml:lang="zh">天工LCI数据工作小组</common:shortDescription>
			</common:referenceToOwnershipOfDataSet>
			<common:copyright>false</common:copyright>
			<common:licenseType>Free of charge for all users and uses</common:licenseType>
		</publicationAndOwnership>
	</administrativeInformation>
	<exchanges>
		<exchange dataSetInternalID="0">
			<referenceToFlowDataSet type="flow data set" refObjectId="4f1a3f41-7b3b-11dd-ad8b-0800200c9a66" uri="../flows/4f1a3f41-7b3b-11dd-ad8b-0800200c9a66.xml">
				<common:shortDescription xml:lang="en">waste water - untreated</common:shortDescription>
			</referenceToFlowDataSet>
			<exchangeDirection>Input</exchangeDirection>
			<meanAmount>1.0</meanAmount>
			<resultingAmount>1.0</resultingAmount>
			<dataDerivationTypeStatus>Measured</dataDerivationTypeStatus>
		</exchange>
		<exchange dataSetInternalID="1">
			<referenceToFlowDataSet type="flow data set" refObjectId="8215cec6-029b-4297-a8c2-6f893b1f8412" uri="../flows/8215cec6-029b-4297-a8c2-6f893b1f8412.xml">
				<common:shortDescription xml:lang="en">waste water - treated</common:shortDescription>
			</referenceToFlowDataSet>
			<exchangeDirection>Output</exchangeDirection>
			<meanAmount>1.0</meanAmount>
			<resultingAmount>1.0</resultingAmount>
			<dataDerivationTypeStatus>Measured</dataDerivationTypeStatus>
		</exchange>
		<exchange dataSetInternalID="2">
			<referenceToFlowDataSet type="flow data set" refObjectId="5cad53b5-252a-4e2f-8197-8be465707405" uri="../flows/5cad53b5-252a-4e2f-8197-8be465707405.xml">
				<common:shortDescription xml:lang="en">Activated Carbon</common:shortDescription>
			</referenceToFlowDataSet>
			<exchangeDirection>Input</exchangeDirection>
			<meanAmount>28.62</meanAmount>
			<resultingAmount>28.62</resultingAmount>
			<dataDerivationTypeStatus>Measured</dataDerivationTypeStatus>
		</exchange>
		<exchange dataSetInternalID="3">
			<referenceToFlowDataSet type="flow data set" refObjectId="0d7a3ad3-6556-11dd-ad8b-0800200c9a66" uri="../flows/0d7a3ad3-6556-11dd-ad8b-0800200c9a66.xml">
				<common:shortDescription xml:lang="en">quartz sand</common:shortDescription>
			</referenceToFlowDataSet>
			<exchangeDirection>Input</exchangeDirection>
			<meanAmount>87.2</meanAmount>
			<resultingAmount>87.2</resultingAmount>
			<dataDerivationTypeStatus>Measured</dataDerivationTypeStatus>
		</exchange>
		<exchange dataSetInternalID="4">
			<referenceToFlowDataSet type="flow data set" refObjectId="890a70b7-b677-4e2a-8a1b-7d017e0a10ae" uri="../flows/890a70b7-b677-4e2a-8a1b-7d017e0a10ae.xml">
				<common:shortDescription xml:lang="en">Electricity</common:shortDescription>
			</referenceToFlowDataSet>
			<exchangeDirection>Input</exchangeDirection>
			<meanAmount>939.8879999999999</meanAmount>
			<resultingAmount>939.8879999999999</resultingAmount>
			<dataDerivationTypeStatus>Measured</dataDerivationTypeStatus>
		</exchange>
		<exchange dataSetInternalID="5">
			<referenceToFlowDataSet type="flow data set" refObjectId="f1b285a5-2733-450c-af08-69e960b671ee" uri="../flows/f1b285a5-2733-450c-af08-69e960b671ee.xml">
				<common:shortDescription xml:lang="en">Polyaluminium Chloride</common:shortDescription>
			</referenceToFlowDataSet>
			<exchangeDirection>Input</exchangeDirection>
			<meanAmount>5.57</meanAmount>
			<resultingAmount>5.57</resultingAmount>
			<dataDerivationTypeStatus>Measured</dataDerivationTypeStatus>
		</exchange>
	</exchanges>
</processDataSet>
