<?xml version="1.0" encoding="utf-8"?>
<?xml-stylesheet version="1.0" href="../../stylesheets/process2html.xsl" type="text/xsl"?>
<processDataSet xmlns="http://lca.jrc.it/ILCD/Process" xmlns:common="http://lca.jrc.it/ILCD/Common" xmlns:xsi="http://www.w3.org/2001/XMLSchema-instance" version="1.1" locations="../ILCDLocations.xml" xsi:schemaLocation="http://lca.jrc.it/ILCD/Process ../../schemas/ILCD_ProcessDataSet.xsd">
	<processInformation>
		<dataSetInformation>
			<common:UUID>9049c196-0d06-4c3e-9bb3-404f557053eb</common:UUID>
			<name>
				<baseName xml:lang="en">Mine water treatment plant ; Lignite ; Lignite ; Underground machine mining ; greater than or equal to1.2 million t/a; NESPS2</baseName>
				<baseName xml:lang="zh">矿井水处理站 ; 褐煤 ; 褐煤 ; 井工机采 ; 大于等于120万吨/年 ; 贫水地区 ; 全国第二次污染普查数据</baseName>
			</name>
			<common:generalComment xml:lang="en">the Technical of end-of-pipe management technology for pollution arsenicisPhysicochemical treatment，Its Technical efficiency of end-of-pipe management85，The formula for calculating the actual operation rate (k-value) of the end-of-pipe treatment facility is k = annual operating time of wastewater treatment facilities (hours/year) / normal production time (hours/year)</common:generalComment>
			<classificationInformation>
				<common:classification>
					<common:class level="0">Energy carriers and technologies</common:class>
					<common:class level="1">Lignite based fuels</common:class>
				</common:classification>
			</classificationInformation>
		</dataSetInformation>
		<quantitativeReference type="Reference flow(s)">
			<referenceToReferenceFlow>3</referenceToReferenceFlow>
		</quantitativeReference>
		<time>
			<common:referenceYear>2019</common:referenceYear>
		</time>
		<geography>
			<locationOfOperationSupplyOrProduction location="CN"/>
		</geography>
		<technology>
			<technologyDescriptionAndIncludedProcesses xml:lang="en">the Technical of end-of-pipe management technology for pollution arsenicisPhysicochemical treatment，Its Technical efficiency of end-of-pipe management85，The formula for calculating the actual operation rate (k-value) of the end-of-pipe treatment facility is k = annual operating time of wastewater treatment facilities (hours/year) / normal production time (hours/year)</technologyDescriptionAndIncludedProcesses>
			<technologicalApplicability xml:lang="zh">该工业过程描述了一座矿井水处理设施的运营情况，该矿井为褐煤地下机械采矿作业，产量大于或等于每年120万吨。该设施专注于通过理化方法处理废水，以去除化学需氧量、石油相关废物、汞和砷等污染物，其处理效率对于化学需氧量和石油相关废物为95%，对于汞和砷为85%。</technologicalApplicability>
		</technology>
	</processInformation>
	<modellingAndValidation>
		<LCIMethodAndAllocation>
			<typeOfDataSet>Unit process, single operation</typeOfDataSet>
		</LCIMethodAndAllocation>
		<dataSourcesTreatmentAndRepresentativeness>
			<deviationsFromTreatmentAndExtrapolationPrinciples xml:lang="en">None</deviationsFromTreatmentAndExtrapolationPrinciples>
			<referenceToDataSource type="source data set" refObjectId="4aba8861-c65e-4b50-b829-6a0cfcb17e2c" uri="../sources/4aba8861-c65e-4b50-b829-6a0cfcb17e2c.xml">
				<common:shortDescription xml:lang="en">第二次全国污染源普查产排污核算系数手册（试用版）,二级代码06,三级代码62.0,四级代码620文件，在完整版文件中第22页</common:shortDescription>
			</referenceToDataSource>
			<useAdviceForDataSet xml:lang="en">This dataset is derived from the Pollution Source Census Report and contains information on pollution emissions and related products. However, it does not include data on energy or chemical consumption, nor does it provide information on waste or co-product generation. When utilizing this dataset, please supplement the missing data based on actual conditions before use</useAdviceForDataSet>
			<useAdviceForDataSet xml:lang="zh">该数据集来源于污染源普查报告，包含污染物排放及相关产品信息，但不包含能源或化学品消耗数据，也不提供废弃物或共生产物产生信息。在使用该数据集时，请根据实际情况补充缺失数据后再使用。</useAdviceForDataSet>
		</dataSourcesTreatmentAndRepresentativeness>
		<completeness/>
		<validation>
			<review type="Dependent internal review">
				<common:reviewDetails xml:lang="en">Inventory: The internal review was done by several iteration steps concerning raw data validation, raw data documentation, representativity, completeness and consistency of modelling with regard to ISO 14040 and 14044.</common:reviewDetails>
				<common:reviewDetails xml:lang="zh">清单： 内部审查通过几个迭代步骤完成，涉及原始数据验证、原始数据记录、代表性、完整性、与 ISO 14040 和 14044 有关的建模的一致性。</common:reviewDetails>
				<common:referenceToNameOfReviewerAndInstitution refObjectId="f4b4c314-8c4c-4c83-968f-5b3c7724f6a8" type="contact data set" uri="../contacts/f4b4c314-8c4c-4c83-968f-5b3c7724f6a8.xml">
					<common:shortDescription xml:lang="en">Tiangong LCI Data Working Group</common:shortDescription>
					<common:shortDescription xml:lang="zh">天工LCI数据工作小组</common:shortDescription>
				</common:referenceToNameOfReviewerAndInstitution>
			</review>
		</validation>
	</modellingAndValidation>
	<administrativeInformation>
		<dataGenerator>
			<common:referenceToPersonOrEntityGeneratingTheDataSet type="contact data set" refObjectId="5236c70e-03a1-4c84-aacf-3dd5d4f9b3ab" uri="../contacts/5236c70e-03a1-4c84-aacf-3dd5d4f9b3ab.xml" version="01.00.000">
				<common:shortDescription xml:lang="en">The data was created by the Office of the Second National Pollution Source Census of the Ministry of Ecology and Environment, and the data was organized by the TianGong Plan team for ILCD format</common:shortDescription>
				<common:shortDescription xml:lang="zh">生态环境部第二次全国污染源普查工作办公室创建数据，天工计划团队常慧敏整理数据为ILCD格式</common:shortDescription>
			</common:referenceToPersonOrEntityGeneratingTheDataSet>
		</dataGenerator>
		<dataEntryBy/>
		<publicationAndOwnership>
			<common:dateOfLastRevision>2024-01-27T10:11:19.606248+08:00</common:dateOfLastRevision>
			<common:dataSetVersion>00.01.004</common:dataSetVersion>
			<common:permanentDataSetURI>https://lcadata.tiangong.world/showProcess.xhtml?uuid=9049c196-0d06-4c3e-9bb3-404f557053eb&amp;amp;version=01.00.000&amp;amp;stock=TianGong</common:permanentDataSetURI>
			<common:referenceToOwnershipOfDataSet refObjectId="f4b4c314-8c4c-4c83-968f-5b3c7724f6a8" type="contact data set" uri="../contacts/f4b4c314-8c4c-4c83-968f-5b3c7724f6a8.xml">
				<common:shortDescription xml:lang="en">Tiangong LCI Data Working Group</common:shortDescription>
				<common:shortDescription xml:lang="zh">天工LCI数据工作小组</common:shortDescription>
			</common:referenceToOwnershipOfDataSet>
			<common:copyright>false</common:copyright>
			<common:licenseType>Free of charge for all users and uses</common:licenseType>
		</publicationAndOwnership>
	</administrativeInformation>
	<exchanges>
		<exchange dataSetInternalID="0">
			<referenceToFlowDataSet type="flow data set" refObjectId="fe0acd60-3ddc-11dd-a8ca-0050c2490048" uri="../flows/fe0acd60-3ddc-11dd-a8ca-0050c2490048.xml">
				<common:shortDescription xml:lang="en">Mercury</common:shortDescription>
			</referenceToFlowDataSet>
			<exchangeDirection>Output</exchangeDirection>
			<meanAmount>7.5e-09</meanAmount>
			<resultingAmount>7.5e-09</resultingAmount>
			<dataDerivationTypeStatus>Calculated</dataDerivationTypeStatus>
			<generalComment xml:lang="en">the Technical of end-of-pipe management technology for pollution MercuryisPhysicochemical treatment，Its Technical efficiency of end-of-pipe management85，The formula for calculating the actual operation rate (k-value) of the end-of-pipe treatment facility is k = annual operating time of wastewater treatment facilities (hours/year) / normal production time (hours/year)</generalComment>
			<generalComment xml:lang="zh">污染物指标汞的末端治理技术是物理化学处理法，其效率为85，末端治理设施实际运行率（k值）计算公式为k=处理设施正常运行时间（天/年）/企业正常生产时间（天/年）。原文件中描述污染物类别为废水，污染物指标为汞，此处对其进行了匹配工作，将其匹配到LCAflow库里面相最符合的流</generalComment>
		</exchange>
		<exchange dataSetInternalID="1">
			<referenceToFlowDataSet type="flow data set" refObjectId="7976a2f9-03eb-4b55-b4eb-b3effc86fe1d" uri="../flows/7976a2f9-03eb-4b55-b4eb-b3effc86fe1d.xml">
				<common:shortDescription xml:lang="en">Petroleum-related waste</common:shortDescription>
			</referenceToFlowDataSet>
			<exchangeDirection>Output</exchangeDirection>
			<meanAmount>3.4000000000000007e-05</meanAmount>
			<resultingAmount>3.4000000000000007e-05</resultingAmount>
			<dataDerivationTypeStatus>Calculated</dataDerivationTypeStatus>
			<generalComment xml:lang="en">the Technical of end-of-pipe management technology for pollution Petroleum-related wasteisPhysicochemical treatment，Its Technical efficiency of end-of-pipe management95，The formula for calculating the actual operation rate (k-value) of the end-of-pipe treatment facility is k = annual operating time of wastewater treatment facilities (hours/year) / normal production time (hours/year)</generalComment>
			<generalComment xml:lang="zh">污染物指标石油类的末端治理技术是物理化学处理法，其效率为95，末端治理设施实际运行率（k值）计算公式为k=处理设施正常运行时间（天/年）/企业正常生产时间（天/年）。原文件中描述污染物类别为废水，污染物指标为石油类，此处对其进行了匹配工作，将其匹配到LCAflow库里面相最符合的流</generalComment>
		</exchange>
		<exchange dataSetInternalID="2">
			<referenceToFlowDataSet type="flow data set" refObjectId="72721c4e-d589-4ad7-8c5e-4228b8690ddb" uri="../flows/72721c4e-d589-4ad7-8c5e-4228b8690ddb.xml">
				<common:shortDescription xml:lang="en">Waste water</common:shortDescription>
			</referenceToFlowDataSet>
			<exchangeDirection>Output</exchangeDirection>
			<meanAmount>320.0</meanAmount>
			<resultingAmount>320.0</resultingAmount>
			<dataDerivationTypeStatus>Calculated</dataDerivationTypeStatus>
			<generalComment xml:lang="en">the treatment technology for the pollution of Waste waterdidn't offered，The formula for calculating the actual operation rate (k-value) of the end-of-pipe treatment facility is k = annual operating time of wastewater treatment facilities (hours/year) / normal production time (hours/year)</generalComment>
			<generalComment xml:lang="zh">污染物指标工业废水量的末端治理技术未说明，末端治理设施实际运行率（k值）计算公式为k=处理设施正常运行时间（天/年）/企业正常生产时间（天/年）。原文件中描述污染物类别为废水，污染物指标为工业废水量，此处对其进行了匹配工作，将其匹配到LCAflow库里面相最符合的流</generalComment>
		</exchange>
		<exchange dataSetInternalID="3">
			<referenceToFlowDataSet type="flow data set" refObjectId="fe0acd60-3ddc-11dd-a6f9-0050c2490048" uri="../flows/fe0acd60-3ddc-11dd-a6f9-0050c2490048.xml">
				<common:shortDescription xml:lang="en">brown coal;  11.9 MJ/kg</common:shortDescription>
			</referenceToFlowDataSet>
			<exchangeDirection>Input</exchangeDirection>
			<meanAmount>1000.0</meanAmount>
			<resultingAmount>1000.0</resultingAmount>
			<dataDerivationTypeStatus>Calculated</dataDerivationTypeStatus>
			<generalComment xml:lang="en">nan</generalComment>
			<generalComment xml:lang="zh">源文件中描述为为褐煤，此处对其进行了匹配工作，将其匹配到LCAflow库里面相最符合的流</generalComment>
		</exchange>
		<exchange dataSetInternalID="4">
			<referenceToFlowDataSet type="flow data set" refObjectId="08a91e70-3ddc-11dd-97ef-0050c2490048" uri="../flows/08a91e70-3ddc-11dd-97ef-0050c2490048.xml">
				<common:shortDescription xml:lang="en">chemical oxygen demand</common:shortDescription>
			</referenceToFlowDataSet>
			<exchangeDirection>Output</exchangeDirection>
			<meanAmount>0.00145</meanAmount>
			<resultingAmount>0.00145</resultingAmount>
			<dataDerivationTypeStatus>Calculated</dataDerivationTypeStatus>
			<generalComment xml:lang="en">the Technical of end-of-pipe management technology for pollution chemical oxygen demandisPhysicochemical treatment，Its Technical efficiency of end-of-pipe management95，The formula for calculating the actual operation rate (k-value) of the end-of-pipe treatment facility is k = annual operating time of wastewater treatment facilities (hours/year) / normal production time (hours/year)</generalComment>
			<generalComment xml:lang="zh">污染物指标化学需氧量的末端治理技术是物理化学处理法，其效率为95，末端治理设施实际运行率（k值）计算公式为k=处理设施正常运行时间（天/年）/企业正常生产时间（天/年）。原文件中描述污染物类别为废水，污染物指标为化学需氧量，此处对其进行了匹配工作，将其匹配到LCAflow库里面相最符合的流</generalComment>
		</exchange>
		<exchange dataSetInternalID="5">
			<referenceToFlowDataSet type="flow data set" refObjectId="08a91e70-3ddc-11dd-91e1-0050c2490048" uri="../flows/08a91e70-3ddc-11dd-91e1-0050c2490048.xml">
				<common:shortDescription xml:lang="en">arsenic</common:shortDescription>
			</referenceToFlowDataSet>
			<exchangeDirection>Output</exchangeDirection>
			<meanAmount>3.84e-06</meanAmount>
			<resultingAmount>3.84e-06</resultingAmount>
			<dataDerivationTypeStatus>Calculated</dataDerivationTypeStatus>
			<generalComment xml:lang="en">the Technical of end-of-pipe management technology for pollution arsenicisPhysicochemical treatment，Its Technical efficiency of end-of-pipe management85，The formula for calculating the actual operation rate (k-value) of the end-of-pipe treatment facility is k = annual operating time of wastewater treatment facilities (hours/year) / normal production time (hours/year)</generalComment>
			<generalComment xml:lang="zh">污染物指标砷的末端治理技术是物理化学处理法，其效率为85，末端治理设施实际运行率（k值）计算公式为k=处理设施正常运行时间（天/年）/企业正常生产时间（天/年）。原文件中描述污染物类别为废水，污染物指标为砷，此处对其进行了匹配工作，将其匹配到LCAflow库里面相最符合的流</generalComment>
		</exchange>
	</exchanges>
</processDataSet>
